mh_python/__init__.py
mh_python-0.0.12.dist-info/LICENSE.AGPL
mh_python-0.0.12.dist-info/METADATA
mh_python-0.0.12.dist-info/WHEEL
mh_python-0.0.12.dist-info/entry_points.txt
mh_python-0.0.12.dist-info/top_level.txt
mh_python-0.0.12.dist-info/RECORD
