Metadata-Version: 2.1
Name: mh-python
Version: 0.0.12
Summary: Matlab to Python/Numpy translator
Home-page: https://translate.mat2py.org
Author: Chaoqing Wang
Author-email: chaoqingwang.nick@gmail.com
License: GNU Affero General Public License v3
Classifier: Development Status :: 2 - Pre-Alpha
Classifier: Intended Audience :: Developers
Classifier: License :: OSI Approved :: GNU Affero General Public License v3 or later (AGPLv3+)
Classifier: Operating System :: OS Independent
Classifier: Programming Language :: Python :: 3
Classifier: Topic :: Scientific/Engineering
Classifier: Topic :: Software Development :: Compilers
Classifier: Topic :: Software Development :: Quality Assurance
Classifier: Topic :: Utilities
Requires-Python: >=3.6, <4
License-File: LICENSE.AGPL
Requires-Dist: miss-hit-core (==0.9.30)
